antiFloating/__init__.py
antiFloating/antiFloating.py
antifloating-1.0.0.0.dist-info/METADATA
antifloating-1.0.0.0.dist-info/WHEEL
antifloating-1.0.0.0.dist-info/top_level.txt
antifloating-1.0.0.0.dist-info/RECORD
