Metadata-Version: 2.1
Name: antifloating
Version: 1.0.0.0
Summary: do not make floating point error
Home-page: https://github.com/htlim07
Author: Hyeongtaek Lim
Author-email: htlim07@gmail.com
License: MIT
Requires-Python: >=3
